genz_tokenize/VERSION
genz_tokenize/__init__.py
genz_tokenize/preprocess.py
genz_tokenize/ranking.py
genz_tokenize/tokenize.py
genz_tokenize/data/bpe.codes
genz_tokenize/data/vocab.txt
genz_tokenize/models/__init__.py
genz_tokenize/models/base_model/__init__.py
genz_tokenize/models/base_model/layers.py
genz_tokenize/models/base_model/models.py
genz_tokenize/models/base_model/training.py
genz_tokenize/models/base_model/utils.py
genz_tokenize/models/bert/__init__.py
genz_tokenize/models/bert/dataset.py
genz_tokenize/models/bert/model_utils.py
genz_tokenize/models/bert/training.py
genz_tokenize/models/bert/distilbert/__init__.py
genz_tokenize/models/bert/distilbert/config.py
genz_tokenize/models/bert/distilbert/layers.py
genz_tokenize/models/bert/distilbert/models.py
genz_tokenize/models/bert/roberta/__init__.py
genz_tokenize/models/bert/roberta/config.py
genz_tokenize/models/bert/roberta/layers.py
genz_tokenize/models/bert/roberta/models.py
genz_tokenize-1.2.7.dist-info/LICENSE
genz_tokenize-1.2.7.dist-info/METADATA
genz_tokenize-1.2.7.dist-info/WHEEL
genz_tokenize-1.2.7.dist-info/top_level.txt
genz_tokenize-1.2.7.dist-info/RECORD
