Metadata-Version: 2.1
Name: genz-tokenize
Version: 1.2.7
Summary: Vietnamese tokenization, preprocess and models NLP
Home-page: https://github.com/nghiemIUH/genz-tokenize
Author: Van Nghiem
Author-email: vannghiem848@gmail.com
License: MIT
Keywords: natural language processing BERT transformer seq2seq
Platform: UNKNOWN
Classifier: Intended Audience :: Developers
Classifier: License :: OSI Approved :: MIT License
Classifier: Programming Language :: Python :: 3
Classifier: Operating System :: OS Independent
Requires-Python: >=3.7
Requires-Dist: tensorflow
Requires-Dist: vncorenlp
